[
    {
        "from": [
            115.03204064928966,
            35.705833879681272
        ],
        "to": [
            115.01846156785787,
            35.722862130110052
        ],
        "weight": 116
    },
    {
        "from": [
            115.03675266957364,
            35.724014677616225
        ],
        "to": [
            115.01846156785787,
            35.722862130110052
        ],
        "weight": 56
    },
    {
        "from": [
            115.023,
            35.713
        ],
        "to": [
            115.01846156785787,
            35.722862130110052
        ],
        "weight": 200
    },
    {
        "from": [
            115.01207175600501,
            35.706462793571056
        ],
        "to": [
            115.01846156785787,
            35.722862130110052
        ],
        "weight": 200
    },
    {
        "from": [
            115.03173344264587,
            35.69774324576143
        ],
        "to": [
            115.01846156785787,
            35.722862130110052
        ],
        "weight": 87
    }
]