[
    {
        "from": [
            115.016,
            35.691
        ],
        "to": [
            115.018,
            35.705
        ],
        "weight": 116
    },
    {
        "from": [
            115.036,
            35.698
        ],
        "to": [
            115.018,
            35.705
        ],
        "weight": 56
    },
    {
        "from": [
            115.032,
            35.706
        ],
        "to": [
            115.018,
            35.705
        ],
        "weight": 200
    },
    {
        "from": [
            115.019,
            35.722
        ],
        "to": [
            115.018,
            35.705
        ],
        "weight": 102
    },
    {
        "from": [
            115.038,
            35.72
        ],
        "to": [
            115.018,
            35.705
        ],
        "weight": 87
    },
    {
        "from": [
            115.002,
            35.72
        ],
        "to": [
            115.018,
            35.705
        ],
        "weight": 87
    },
	{
	    "from": [
            115.00,
            35.707
        ],
        "to": [
            115.018,
            35.705
        ],
        "weight": 87
	}
]